r/main.py
pyrapid-0.0.4.dist-info/METADATA
pyrapid-0.0.4.dist-info/WHEEL
pyrapid-0.0.4.dist-info/RECORD
