Metadata-Version: 2.3
Name: pyrapid
Version: 0.0.4
Summary: Build native apps in Python
Project-URL: Homepage, https://github.com/kazhoyan/pyrapid
Project-URL: Issues, https://github.com/kazhoyan/pyrapid/issues
Author-email: Avetik Kazhoyan <kazhoyan@gmail.com>
Classifier: Development Status :: 1 - Planning
Classifier: License :: OSI Approved :: MIT License
Classifier: Operating System :: OS Independent
Classifier: Programming Language :: Python :: 3.12
Requires-Python: >=3.12.3
